MANIFEST.in
README.rst
podcastdl.py
setup.py
podcastdl.egg-info/PKG-INFO
podcastdl.egg-info/SOURCES.txt
podcastdl.egg-info/dependency_links.txt
podcastdl.egg-info/entry_points.txt
podcastdl.egg-info/requires.txt
podcastdl.egg-info/top_level.txt