Metadata-Version: 1.1
Name: podcastdl
Version: 0.2.1
Summary: A simple script to parse a rss and download its mp3 files
Home-page: UNKNOWN
Author: Alexis Metaireau
Author-email: alexis@notmyidea.org
License: UNKNOWN
Platform: UNKNOWN
Classifier: Environment :: Console
Classifier: License :: OSI Approved :: Common Public License
Classifier: Operating System :: OS Independent
Classifier: Programming Language :: Python :: 2.7
Classifier: Topic :: Internet :: WWW/HTTP
